gateway/__init__.py
gateway/accounting.py
gateway/app.py
gateway/auth.py
gateway/cli.py
gateway/config.py
gateway/ipacl.py
gateway/log.py
gateway/main.py
gateway/policies.py
gateway/routing.py
gateway/runtime.py
gateway/scheduling.py
gateway/signals.py
gateway/sse.py
gateway/trace.py
gateway/api/__init__.py
gateway/api/admin.py
gateway/api/v1.py
gateway/backends/__init__.py
gateway/backends/anthropic.py
gateway/backends/base.py
gateway/backends/mistral.py
gateway/backends/ollama.py
gateway/backends/openai.py
gateway/middleware/__init__.py
gateway/middleware/trace.py
mini_apigw-0.0.24.dist-info/licenses/LICENSE.md
mini_apigw-0.0.24.dist-info/METADATA
mini_apigw-0.0.24.dist-info/WHEEL
mini_apigw-0.0.24.dist-info/entry_points.txt
mini_apigw-0.0.24.dist-info/top_level.txt
mini_apigw-0.0.24.dist-info/RECORD
