Metadata-Version: 2.4
Name: mini-apigw
Version: 0.0.24
Summary: Minimal OpenAI-compatible edge gateway with multi-backend routing
Author-email: Thomas Spielauer <pypipackages01@tspi.at>
License-Expression: BSD-3-Clause
Project-URL: Homepage, https://www.github.com/tspspi/mini-apigw
Keywords: API-gateway,gateway,API,LLM
Classifier: Programming Language :: Python :: 3
Classifier: Programming Language :: Python :: 3.9
Classifier: Programming Language :: Python :: 3.10
Classifier: Programming Language :: Python :: 3.11
Classifier: Programming Language :: Python :: 3.12
Classifier: Intended Audience :: Developers
Classifier: Topic :: Internet :: WWW/HTTP
Classifier: Topic :: Scientific/Engineering :: Artificial Intelligence
Requires-Python: >=3.10
License-File: LICENSE.md
Requires-Dist: fastapi>=0.110
Requires-Dist: uvicorn>=0.27
Requires-Dist: daemonize>=2.5
Requires-Dist: httpx>=0.27
Requires-Dist: requests>=2.31
Requires-Dist: openai>=1.0
Requires-Dist: ollama>=0.3
Requires-Dist: mistralai>=1.9.11
Requires-Dist: psycopg2>=2.9.10
Provides-Extra: dev
Requires-Dist: pytest>=7.0; extra == "dev"
Dynamic: license-file
